README.rst
setup.py
catsnap/__init__.py
catsnap/app.py
catsnap/image_metadata.py
catsnap/image_truck.py
catsnap/ordered_set.py
catsnap/reorient_image.py
catsnap/resize_image.py
catsnap/singleton.py
catsnap.egg-info/PKG-INFO
catsnap.egg-info/SOURCES.txt
catsnap.egg-info/dependency_links.txt
catsnap.egg-info/requires.txt
catsnap.egg-info/top_level.txt
catsnap/batch/__init__.py
catsnap/batch/image_batch.py
catsnap/batch/tag_batch.py
catsnap/config/__init__.py
catsnap/config/argument_config.py
catsnap/config/base.py
catsnap/config/env_config.py
catsnap/config/file_config.py
catsnap/document/__init__.py
catsnap/document/image.py
catsnap/document/tag.py
scripts/catsnap