Metadata-Version: 1.0
Name: catsnap
Version: 4.2.0
Summary: catalog and store images
Home-page: github.com/andrewlorente/catsnap
Author: Andrew Lorente
Author-email: andrew.lorente@gmail.com
License: UNKNOWN
Platform: UNKNOWN
